README.rst
setup.py
optioncomplete/__init__.py
optioncomplete/createAutoOptDatabase.py
optioncomplete/optioncomplete.py
optioncomplete.egg-info/PKG-INFO
optioncomplete.egg-info/SOURCES.txt
optioncomplete.egg-info/dependency_links.txt
optioncomplete.egg-info/top_level.txt