Metadata-Version: 1.1
Name: optioncomplete
Version: 2.7
Summary: Autocomplete options for python3 scripts in command line using optparse.
Home-page: UNKNOWN
Author: Adam Csoka
Author-email: csoka.adam@sic.ke.hu
License: UNKNOWN
Keywords: optparse,optioncomplete,autocomplete,commandline
Platform: any
Classifier: Natural Language :: English
Classifier: Programming Language :: Python :: 3
Requires: optparser
Requires: mysqlclient
